pytest_browsermob_proxy.py
setup.py
pytest_browsermob_proxy.egg-info/PKG-INFO
pytest_browsermob_proxy.egg-info/SOURCES.txt
pytest_browsermob_proxy.egg-info/dependency_links.txt
pytest_browsermob_proxy.egg-info/entry_points.txt
pytest_browsermob_proxy.egg-info/requires.txt
pytest_browsermob_proxy.egg-info/top_level.txt